{
  "pessoa":{
    "nome": "João",
    "email": "ricardobatista@teste.com",
    "tipo": "F/J",
    "fisica": {
      "cpf": "123.456.789-00"
    },
    "juridica": {
      "cnpj": "12.345.678/0001-00"
    },
    "contatos": [
      {
        "tipo": "PESSOAL",
        "telefone": "(11) 98765-4321"
      },
      {
        "tipo": "TRABALHO",
        "telefone": "(11) 98765-4321"
      }
    ],
    "enderecos": [
      {
        "logradouro": "Rua das Flores",
        "numero": 123,
        "bairro": "Jardim das Rosas",
        "cidade": "São Paulo",
        "uf": "SP",
        "cep": "77814-812",
        "tipoEndereco": "RESIDENCIAL"
      }
    ],
    "cadastro":"2024-06-01",
    "observacao": ""
  },
  "colaborador": {
    "matricula": "12348",
    "cargo": {
      "id":"id-cargo",
      "nome": "Desenvolvedor de Software",
      "salario": 5000.00
    },
    "departamento": {
      "id":"id-departamento",
      "nome": "Tecnologia da Informação"
    },
    "vendedor": {
      "comissao": 0.05,
      "metaVendas": 100000.00
    }
  },
  "cliente": {
    "taxaDesconto": 0.1,
    "limiteCredito": 10000
  },
  "createUser":true
}